{
	"info": {
		"_postman_id": "d3084f62-060c-4d1e-9ab4-7094e14cd2ee",
		"name": "Facegram",
		"schema": "https://schema.getpostman.com/json/collection/v2.1.0/collection.json",
		"_exporter_id": "26111357"
	},
	"item": [
		{
			"name": "Authentication",
			"item": [
				{
					"name": "Register",
					"item": [
						{
							"name": "Register - success",
							"event": [
								{
									"listen": "test",
									"script": {
										"exec": [
											"const json = JSON.parse(responseBody)",
											"if(json?.token) {",
											"    pm.collectionVariables.set(\"token\", json.token);",
											"}"
										],
										"type": "text/javascript"
									}
								}
							],
							"request": {
								"method": "POST",
								"header": [
									{
										"key": "Accept",
										"value": "application/json",
										"type": "text"
									}
								],
								"body": {
									"mode": "raw",
									"raw": "{\n    \"full_name\": \"Budi Budiman\",\n    \"username\": \"budi.budiman\",\n    \"password\": \"pass123\",\n    \"bio\": \"stop dreaming, start doing\",\n    \"is_private\": true\n}",
									"options": {
										"raw": {
											"language": "json"
										}
									}
								},
								"url": {
									"raw": "{{host}}/api/v1/auth/register",
									"host": [
										"{{host}}"
									],
									"path": [
										"api",
										"v1",
										"auth",
										"register"
									]
								}
							},
							"response": []
						},
						{
							"name": "Register - invalid field",
							"request": {
								"method": "POST",
								"header": [
									{
										"key": "Accept",
										"value": "application/json",
										"type": "text"
									}
								],
								"body": {
									"mode": "raw",
									"raw": "{ \n    \"username\": \"john doe\",\n    \"password\": \"puc\",\n    \"is_private\": \"yes\"\n}",
									"options": {
										"raw": {
											"language": "json"
										}
									}
								},
								"url": {
									"raw": "{{host}}/api/v1/auth/register",
									"host": [
										"{{host}}"
									],
									"path": [
										"api",
										"v1",
										"auth",
										"register"
									]
								}
							},
							"response": []
						}
					]
				},
				{
					"name": "Login",
					"item": [
						{
							"name": "Login - success",
							"event": [
								{
									"listen": "test",
									"script": {
										"exec": [
											"const json = JSON.parse(responseBody)",
											"if(json?.token) {",
											"    pm.collectionVariables.set(\"token\", json.token);",
											"}"
										],
										"type": "text/javascript"
									}
								}
							],
							"request": {
								"method": "POST",
								"header": [
									{
										"key": "Accept",
										"value": "application/json",
										"type": "text"
									}
								],
								"body": {
									"mode": "raw",
									"raw": "{ \n    \"username\": \"john.doe\",\n    \"password\": \"pass123\"\n}",
									"options": {
										"raw": {
											"language": "json"
										}
									}
								},
								"url": {
									"raw": "{{host}}/api/v1/auth/login",
									"host": [
										"{{host}}"
									],
									"path": [
										"api",
										"v1",
										"auth",
										"login"
									]
								}
							},
							"response": []
						},
						{
							"name": "Login another user - success",
							"event": [
								{
									"listen": "test",
									"script": {
										"exec": [
											"const json = JSON.parse(responseBody)",
											"if(json?.token) {",
											"    pm.collectionVariables.set(\"token\", json.token);",
											"}"
										],
										"type": "text/javascript"
									}
								}
							],
							"request": {
								"method": "POST",
								"header": [
									{
										"key": "Accept",
										"value": "application/json",
										"type": "text"
									}
								],
								"body": {
									"mode": "raw",
									"raw": "{ \n    \"username\": \"richard.roe\",\n    \"password\": \"pass123\"\n}",
									"options": {
										"raw": {
											"language": "json"
										}
									}
								},
								"url": {
									"raw": "{{host}}/api/v1/auth/login",
									"host": [
										"{{host}}"
									],
									"path": [
										"api",
										"v1",
										"auth",
										"login"
									]
								}
							},
							"response": []
						},
						{
							"name": "Login - failed",
							"request": {
								"method": "POST",
								"header": [
									{
										"key": "Accept",
										"value": "application/json",
										"type": "text"
									}
								],
								"body": {
									"mode": "raw",
									"raw": "{ \n    \"username\": \"john.doe\",\n    \"password\": \"wrongpass\"\n}",
									"options": {
										"raw": {
											"language": "json"
										}
									}
								},
								"url": {
									"raw": "{{host}}/api/v1/auth/login",
									"host": [
										"{{host}}"
									],
									"path": [
										"api",
										"v1",
										"auth",
										"login"
									]
								}
							},
							"response": []
						}
					]
				},
				{
					"name": "Logout",
					"item": [
						{
							"name": "Logout - success",
							"request": {
								"method": "POST",
								"header": [
									{
										"key": "Accept",
										"value": "application/json",
										"type": "text"
									}
								],
								"body": {
									"mode": "raw",
									"raw": "",
									"options": {
										"raw": {
											"language": "json"
										}
									}
								},
								"url": {
									"raw": "{{host}}/api/v1/auth/logout",
									"host": [
										"{{host}}"
									],
									"path": [
										"api",
										"v1",
										"auth",
										"logout"
									]
								}
							},
							"response": []
						},
						{
							"name": "Logout - invalid token",
							"request": {
								"auth": {
									"type": "noauth"
								},
								"method": "POST",
								"header": [
									{
										"key": "Accept",
										"value": "application/json",
										"type": "text"
									}
								],
								"body": {
									"mode": "raw",
									"raw": "",
									"options": {
										"raw": {
											"language": "json"
										}
									}
								},
								"url": {
									"raw": "{{host}}/api/v1/auth/logout",
									"host": [
										"{{host}}"
									],
									"path": [
										"api",
										"v1",
										"auth",
										"logout"
									]
								}
							},
							"response": []
						}
					]
				}
			]
		},
		{
			"name": "Post",
			"item": [
				{
					"name": "Create a Post",
					"item": [
						{
							"name": "Create a Post - success",
							"request": {
								"method": "POST",
								"header": [
									{
										"key": "Accept",
										"value": "application/json",
										"type": "text"
									}
								],
								"body": {
									"mode": "formdata",
									"formdata": [
										{
											"key": "caption",
											"value": "Paris 🇫🇷",
											"type": "text"
										},
										{
											"key": "attachments[0]",
											"type": "file",
											"src": "/Users/irfnmaulaa/Downloads/1.jpeg"
										},
										{
											"key": "attachments[1]",
											"type": "file",
											"src": [],
											"disabled": true
										},
										{
											"key": "attachments[2]",
											"type": "file",
											"src": [],
											"disabled": true
										}
									]
								},
								"url": {
									"raw": "{{host}}/api/v1/posts",
									"host": [
										"{{host}}"
									],
									"path": [
										"api",
										"v1",
										"posts"
									]
								}
							},
							"response": []
						},
						{
							"name": "Create a Post - invalid field",
							"request": {
								"method": "POST",
								"header": [
									{
										"key": "Accept",
										"value": "application/json",
										"type": "text"
									}
								],
								"body": {
									"mode": "formdata",
									"formdata": [
										{
											"key": "caption",
											"value": "",
											"type": "text"
										},
										{
											"key": "attachments[0]",
											"type": "file",
											"src": [],
											"disabled": true
										},
										{
											"key": "attachments[1]",
											"type": "file",
											"src": [],
											"disabled": true
										}
									]
								},
								"url": {
									"raw": "{{host}}/api/v1/posts",
									"host": [
										"{{host}}"
									],
									"path": [
										"api",
										"v1",
										"posts"
									]
								}
							},
							"response": []
						},
						{
							"name": "Create a Post - invalid token",
							"request": {
								"auth": {
									"type": "noauth"
								},
								"method": "POST",
								"header": [
									{
										"key": "Accept",
										"value": "application/json",
										"type": "text"
									}
								],
								"body": {
									"mode": "formdata",
									"formdata": [
										{
											"key": "caption",
											"value": "",
											"type": "text"
										},
										{
											"key": "attachments[0]",
											"type": "file",
											"src": [],
											"disabled": true
										},
										{
											"key": "attachments[1]",
											"type": "file",
											"src": [],
											"disabled": true
										}
									]
								},
								"url": {
									"raw": "{{host}}/api/v1/posts",
									"host": [
										"{{host}}"
									],
									"path": [
										"api",
										"v1",
										"posts"
									]
								}
							},
							"response": []
						}
					]
				},
				{
					"name": "Delete Post",
					"item": [
						{
							"name": "Delete Post - success",
							"request": {
								"method": "DELETE",
								"header": [
									{
										"key": "Accept",
										"value": "application/json",
										"type": "text"
									}
								],
								"body": {
									"mode": "raw",
									"raw": "",
									"options": {
										"raw": {
											"language": "json"
										}
									}
								},
								"url": {
									"raw": "{{host}}/api/v1/posts/1",
									"host": [
										"{{host}}"
									],
									"path": [
										"api",
										"v1",
										"posts",
										"1"
									]
								}
							},
							"response": []
						},
						{
							"name": "Delete Post - not found",
							"request": {
								"method": "DELETE",
								"header": [
									{
										"key": "Accept",
										"value": "application/json",
										"type": "text"
									}
								],
								"body": {
									"mode": "formdata",
									"formdata": []
								},
								"url": {
									"raw": "{{host}}/api/v1/posts/9999",
									"host": [
										"{{host}}"
									],
									"path": [
										"api",
										"v1",
										"posts",
										"9999"
									]
								}
							},
							"response": []
						},
						{
							"name": "Delete Post - forbidden",
							"request": {
								"method": "DELETE",
								"header": [
									{
										"key": "Accept",
										"value": "application/json",
										"type": "text"
									}
								],
								"body": {
									"mode": "formdata",
									"formdata": []
								},
								"url": {
									"raw": "{{host}}/api/v1/posts/50",
									"host": [
										"{{host}}"
									],
									"path": [
										"api",
										"v1",
										"posts",
										"50"
									]
								}
							},
							"response": []
						},
						{
							"name": "Delete Post - invalid token",
							"request": {
								"auth": {
									"type": "noauth"
								},
								"method": "DELETE",
								"header": [
									{
										"key": "Accept",
										"value": "application/json",
										"type": "text"
									}
								],
								"body": {
									"mode": "formdata",
									"formdata": []
								},
								"url": {
									"raw": "{{host}}/api/v1/posts/1",
									"host": [
										"{{host}}"
									],
									"path": [
										"api",
										"v1",
										"posts",
										"1"
									]
								}
							},
							"response": []
						}
					]
				},
				{
					"name": "Get Posts",
					"item": [
						{
							"name": "Get Posts - default",
							"request": {
								"method": "GET",
								"header": [
									{
										"key": "Accept",
										"value": "application/json",
										"type": "text"
									}
								],
								"url": {
									"raw": "{{host}}/api/v1/posts",
									"host": [
										"{{host}}"
									],
									"path": [
										"api",
										"v1",
										"posts"
									]
								}
							},
							"response": []
						},
						{
							"name": "Get Posts - get first 5 posts",
							"request": {
								"method": "GET",
								"header": [
									{
										"key": "Accept",
										"value": "application/json",
										"type": "text"
									}
								],
								"url": {
									"raw": "{{host}}/api/v1/posts?page=0&size=5",
									"host": [
										"{{host}}"
									],
									"path": [
										"api",
										"v1",
										"posts"
									],
									"query": [
										{
											"key": "page",
											"value": "0"
										},
										{
											"key": "size",
											"value": "5"
										}
									]
								}
							},
							"response": []
						},
						{
							"name": "Get Posts - get second 5 posts",
							"request": {
								"method": "GET",
								"header": [
									{
										"key": "Accept",
										"value": "application/json",
										"type": "text"
									}
								],
								"url": {
									"raw": "{{host}}/api/v1/posts?page=1&size=5",
									"host": [
										"{{host}}"
									],
									"path": [
										"api",
										"v1",
										"posts"
									],
									"query": [
										{
											"key": "page",
											"value": "1"
										},
										{
											"key": "size",
											"value": "5"
										}
									]
								}
							},
							"response": []
						},
						{
							"name": "Get Posts - invalid params",
							"request": {
								"method": "GET",
								"header": [
									{
										"key": "Accept",
										"value": "application/json",
										"type": "text"
									}
								],
								"url": {
									"raw": "{{host}}/api/v1/posts?page=-1&size=-1",
									"host": [
										"{{host}}"
									],
									"path": [
										"api",
										"v1",
										"posts"
									],
									"query": [
										{
											"key": "page",
											"value": "-1"
										},
										{
											"key": "size",
											"value": "-1"
										}
									]
								}
							},
							"response": []
						}
					]
				}
			]
		},
		{
			"name": "Following",
			"item": [
				{
					"name": "Follow user",
					"item": [
						{
							"name": "Follow user - success",
							"request": {
								"method": "POST",
								"header": [
									{
										"key": "Accept",
										"value": "application/json",
										"type": "text"
									}
								],
								"body": {
									"mode": "formdata",
									"formdata": [
										{
											"key": "username",
											"value": "john.doe",
											"type": "text",
											"disabled": true
										}
									]
								},
								"url": {
									"raw": "{{host}}/api/v1/users/budi.budiman/follow",
									"host": [
										"{{host}}"
									],
									"path": [
										"api",
										"v1",
										"users",
										"budi.budiman",
										"follow"
									]
								}
							},
							"response": []
						},
						{
							"name": "Follow user - user not found",
							"request": {
								"method": "POST",
								"header": [
									{
										"key": "Accept",
										"value": "application/json",
										"type": "text"
									}
								],
								"body": {
									"mode": "formdata",
									"formdata": [
										{
											"key": "username",
											"value": "john.doe",
											"type": "text",
											"disabled": true
										}
									]
								},
								"url": {
									"raw": "{{host}}/api/v1/users/nouser/follow",
									"host": [
										"{{host}}"
									],
									"path": [
										"api",
										"v1",
										"users",
										"nouser",
										"follow"
									]
								}
							},
							"response": []
						},
						{
							"name": "Follow user - not allowed to follow own user account",
							"request": {
								"method": "POST",
								"header": [
									{
										"key": "Accept",
										"value": "application/json",
										"type": "text"
									}
								],
								"body": {
									"mode": "formdata",
									"formdata": []
								},
								"url": {
									"raw": "{{host}}/api/v1/users/john.doe/follow",
									"host": [
										"{{host}}"
									],
									"path": [
										"api",
										"v1",
										"users",
										"john.doe",
										"follow"
									]
								}
							},
							"response": []
						},
						{
							"name": "Follow user - already followed",
							"request": {
								"method": "POST",
								"header": [
									{
										"key": "Accept",
										"value": "application/json",
										"type": "text"
									}
								],
								"body": {
									"mode": "formdata",
									"formdata": []
								},
								"url": {
									"raw": "{{host}}/api/v1/users/richard.roe/follow",
									"host": [
										"{{host}}"
									],
									"path": [
										"api",
										"v1",
										"users",
										"richard.roe",
										"follow"
									]
								}
							},
							"response": []
						},
						{
							"name": "Follow user - invalid token",
							"request": {
								"auth": {
									"type": "noauth"
								},
								"method": "POST",
								"header": [
									{
										"key": "Accept",
										"value": "application/json",
										"type": "text"
									}
								],
								"body": {
									"mode": "formdata",
									"formdata": []
								},
								"url": {
									"raw": "{{host}}/api/v1/users/richard.roe/follow",
									"host": [
										"{{host}}"
									],
									"path": [
										"api",
										"v1",
										"users",
										"richard.roe",
										"follow"
									]
								}
							},
							"response": []
						}
					]
				},
				{
					"name": "Unfollow user",
					"item": [
						{
							"name": "Unfollow user - success",
							"request": {
								"method": "DELETE",
								"header": [
									{
										"key": "Accept",
										"value": "application/json",
										"type": "text"
									}
								],
								"body": {
									"mode": "formdata",
									"formdata": []
								},
								"url": {
									"raw": "{{host}}/api/v1/users/richard.roe/unfollow",
									"host": [
										"{{host}}"
									],
									"path": [
										"api",
										"v1",
										"users",
										"richard.roe",
										"unfollow"
									]
								}
							},
							"response": []
						},
						{
							"name": "Unfollow user - user not found",
							"request": {
								"method": "DELETE",
								"header": [
									{
										"key": "Accept",
										"value": "application/json",
										"type": "text"
									}
								],
								"body": {
									"mode": "formdata",
									"formdata": []
								},
								"url": {
									"raw": "{{host}}/api/v1/users/nouser/unfollow",
									"host": [
										"{{host}}"
									],
									"path": [
										"api",
										"v1",
										"users",
										"nouser",
										"unfollow"
									]
								}
							},
							"response": []
						},
						{
							"name": "Unfollow user - not following",
							"request": {
								"method": "DELETE",
								"header": [
									{
										"key": "Accept",
										"value": "application/json",
										"type": "text"
									}
								],
								"body": {
									"mode": "formdata",
									"formdata": []
								},
								"url": {
									"raw": "{{host}}/api/v1/users/richard.roe/unfollow",
									"host": [
										"{{host}}"
									],
									"path": [
										"api",
										"v1",
										"users",
										"richard.roe",
										"unfollow"
									]
								}
							},
							"response": []
						},
						{
							"name": "Unfollow user - invalid token",
							"request": {
								"auth": {
									"type": "noauth"
								},
								"method": "DELETE",
								"header": [
									{
										"key": "Accept",
										"value": "application/json",
										"type": "text"
									}
								],
								"body": {
									"mode": "formdata",
									"formdata": []
								},
								"url": {
									"raw": "{{host}}/api/v1/users/richard.roe/unfollow",
									"host": [
										"{{host}}"
									],
									"path": [
										"api",
										"v1",
										"users",
										"richard.roe",
										"unfollow"
									]
								}
							},
							"response": []
						}
					]
				},
				{
					"name": "Get following",
					"item": [
						{
							"name": "Get following - success",
							"protocolProfileBehavior": {
								"disableBodyPruning": true
							},
							"request": {
								"method": "GET",
								"header": [
									{
										"key": "Accept",
										"value": "application/json",
										"type": "text"
									}
								],
								"body": {
									"mode": "raw",
									"raw": "",
									"options": {
										"raw": {
											"language": "json"
										}
									}
								},
								"url": {
									"raw": "{{host}}/api/v1/users/john.doe/following",
									"host": [
										"{{host}}"
									],
									"path": [
										"api",
										"v1",
										"users",
										"john.doe",
										"following"
									]
								}
							},
							"response": []
						},
						{
							"name": "Get following - user not found",
							"protocolProfileBehavior": {
								"disableBodyPruning": true
							},
							"request": {
								"method": "GET",
								"header": [
									{
										"key": "Accept",
										"value": "application/json",
										"type": "text"
									}
								],
								"body": {
									"mode": "raw",
									"raw": "",
									"options": {
										"raw": {
											"language": "json"
										}
									}
								},
								"url": {
									"raw": "{{host}}/api/v1/users/nouser/following",
									"host": [
										"{{host}}"
									],
									"path": [
										"api",
										"v1",
										"users",
										"nouser",
										"following"
									]
								}
							},
							"response": []
						},
						{
							"name": "Get following - invalid token",
							"protocolProfileBehavior": {
								"disableBodyPruning": true
							},
							"request": {
								"auth": {
									"type": "noauth"
								},
								"method": "GET",
								"header": [
									{
										"key": "Accept",
										"value": "application/json",
										"type": "text"
									}
								],
								"body": {
									"mode": "raw",
									"raw": "",
									"options": {
										"raw": {
											"language": "json"
										}
									}
								},
								"url": {
									"raw": "{{host}}/api/v1/users/richard.roe/following",
									"host": [
										"{{host}}"
									],
									"path": [
										"api",
										"v1",
										"users",
										"richard.roe",
										"following"
									]
								}
							},
							"response": []
						}
					]
				}
			]
		},
		{
			"name": "Followers",
			"item": [
				{
					"name": "Accept follow request",
					"item": [
						{
							"name": "Accept follow request - success",
							"request": {
								"method": "PUT",
								"header": [
									{
										"key": "Accept",
										"value": "application/json",
										"type": "text"
									}
								],
								"body": {
									"mode": "raw",
									"raw": "",
									"options": {
										"raw": {
											"language": "json"
										}
									}
								},
								"url": {
									"raw": "{{host}}/api/v1/users/john.doe/accept",
									"host": [
										"{{host}}"
									],
									"path": [
										"api",
										"v1",
										"users",
										"john.doe",
										"accept"
									]
								}
							},
							"response": []
						},
						{
							"name": "Accept follow request - user not found",
							"request": {
								"method": "PUT",
								"header": [
									{
										"key": "Accept",
										"value": "application/json",
										"type": "text"
									}
								],
								"body": {
									"mode": "raw",
									"raw": "",
									"options": {
										"raw": {
											"language": "json"
										}
									}
								},
								"url": {
									"raw": "{{host}}/api/v1/users/john.doe/accept",
									"host": [
										"{{host}}"
									],
									"path": [
										"api",
										"v1",
										"users",
										"john.doe",
										"accept"
									]
								}
							},
							"response": []
						},
						{
							"name": "Accept follow request - user not following",
							"request": {
								"method": "PUT",
								"header": [
									{
										"key": "Accept",
										"value": "application/json",
										"type": "text"
									}
								],
								"body": {
									"mode": "raw",
									"raw": "",
									"options": {
										"raw": {
											"language": "json"
										}
									}
								},
								"url": {
									"raw": "{{host}}/api/v1/users/richard.roe/accept",
									"host": [
										"{{host}}"
									],
									"path": [
										"api",
										"v1",
										"users",
										"richard.roe",
										"accept"
									]
								}
							},
							"response": []
						},
						{
							"name": "Accept follow request - already accepted",
							"request": {
								"method": "PUT",
								"header": [
									{
										"key": "Accept",
										"value": "application/json",
										"type": "text"
									}
								],
								"body": {
									"mode": "raw",
									"raw": "",
									"options": {
										"raw": {
											"language": "json"
										}
									}
								},
								"url": {
									"raw": "{{host}}/api/v1/users/john.doe/accept",
									"host": [
										"{{host}}"
									],
									"path": [
										"api",
										"v1",
										"users",
										"john.doe",
										"accept"
									]
								}
							},
							"response": []
						},
						{
							"name": "Accept follow request - invalid token",
							"request": {
								"auth": {
									"type": "noauth"
								},
								"method": "PUT",
								"header": [
									{
										"key": "Accept",
										"value": "application/json",
										"type": "text"
									}
								],
								"body": {
									"mode": "raw",
									"raw": "",
									"options": {
										"raw": {
											"language": "json"
										}
									}
								},
								"url": {
									"raw": "{{host}}/api/v1/users/richard.roe/accept",
									"host": [
										"{{host}}"
									],
									"path": [
										"api",
										"v1",
										"users",
										"richard.roe",
										"accept"
									]
								}
							},
							"response": []
						}
					]
				},
				{
					"name": "Get followers",
					"item": [
						{
							"name": "Get followers - success",
							"protocolProfileBehavior": {
								"disableBodyPruning": true
							},
							"request": {
								"method": "GET",
								"header": [
									{
										"key": "Accept",
										"value": "application/json",
										"type": "text"
									}
								],
								"body": {
									"mode": "raw",
									"raw": "",
									"options": {
										"raw": {
											"language": "json"
										}
									}
								},
								"url": {
									"raw": "{{host}}/api/v1/users/richard.roe/followers",
									"host": [
										"{{host}}"
									],
									"path": [
										"api",
										"v1",
										"users",
										"richard.roe",
										"followers"
									]
								}
							},
							"response": []
						},
						{
							"name": "Get followers - user not found",
							"protocolProfileBehavior": {
								"disableBodyPruning": true
							},
							"request": {
								"method": "GET",
								"header": [
									{
										"key": "Accept",
										"value": "application/json",
										"type": "text"
									}
								],
								"body": {
									"mode": "raw",
									"raw": "",
									"options": {
										"raw": {
											"language": "json"
										}
									}
								},
								"url": {
									"raw": "{{host}}/api/v1/users/nouser/followers",
									"host": [
										"{{host}}"
									],
									"path": [
										"api",
										"v1",
										"users",
										"nouser",
										"followers"
									]
								}
							},
							"response": []
						},
						{
							"name": "Get followers - invalid token",
							"protocolProfileBehavior": {
								"disableBodyPruning": true
							},
							"request": {
								"auth": {
									"type": "noauth"
								},
								"method": "GET",
								"header": [
									{
										"key": "Accept",
										"value": "application/json",
										"type": "text"
									}
								],
								"body": {
									"mode": "raw",
									"raw": "",
									"options": {
										"raw": {
											"language": "json"
										}
									}
								},
								"url": {
									"raw": "{{host}}/api/v1/users/john.doe/followers",
									"host": [
										"{{host}}"
									],
									"path": [
										"api",
										"v1",
										"users",
										"john.doe",
										"followers"
									]
								}
							},
							"response": []
						}
					]
				}
			]
		},
		{
			"name": "User",
			"item": [
				{
					"name": "Get users",
					"item": [
						{
							"name": "Get users - success",
							"request": {
								"method": "GET",
								"header": [
									{
										"key": "Accept",
										"value": "application/json",
										"type": "text"
									}
								],
								"url": {
									"raw": "{{host}}/api/v1/users",
									"host": [
										"{{host}}"
									],
									"path": [
										"api",
										"v1",
										"users"
									]
								}
							},
							"response": []
						},
						{
							"name": "Get users - invalid token",
							"request": {
								"auth": {
									"type": "noauth"
								},
								"method": "GET",
								"header": [
									{
										"key": "Accept",
										"value": "application/json",
										"type": "text"
									}
								],
								"url": {
									"raw": "{{host}}/api/v1/users",
									"host": [
										"{{host}}"
									],
									"path": [
										"api",
										"v1",
										"users"
									]
								}
							},
							"response": []
						}
					]
				},
				{
					"name": "Get detail user",
					"item": [
						{
							"name": "Get detail user - success",
							"request": {
								"method": "GET",
								"header": [
									{
										"key": "Accept",
										"value": "application/json",
										"type": "text"
									}
								],
								"url": {
									"raw": "{{host}}/api/v1/users/richard.roe",
									"host": [
										"{{host}}"
									],
									"path": [
										"api",
										"v1",
										"users",
										"richard.roe"
									]
								}
							},
							"response": []
						},
						{
							"name": "Get detail user - not found",
							"request": {
								"method": "GET",
								"header": [
									{
										"key": "Accept",
										"value": "application/json",
										"type": "text"
									}
								],
								"url": {
									"raw": "{{host}}/api/v1/users/nouser",
									"host": [
										"{{host}}"
									],
									"path": [
										"api",
										"v1",
										"users",
										"nouser"
									]
								}
							},
							"response": []
						},
						{
							"name": "Get detail user - invalid token",
							"request": {
								"auth": {
									"type": "noauth"
								},
								"method": "GET",
								"header": [
									{
										"key": "Accept",
										"value": "application/json",
										"type": "text"
									}
								],
								"url": {
									"raw": "{{host}}/api/v1/users/richard.roe",
									"host": [
										"{{host}}"
									],
									"path": [
										"api",
										"v1",
										"users",
										"richard.roe"
									]
								}
							},
							"response": []
						}
					]
				}
			]
		}
	],
	"auth": {
		"type": "bearer",
		"bearer": [
			{
				"key": "token",
				"value": "{{token}}",
				"type": "string"
			}
		]
	},
	"event": [
		{
			"listen": "prerequest",
			"script": {
				"type": "text/javascript",
				"exec": [
					""
				]
			}
		},
		{
			"listen": "test",
			"script": {
				"type": "text/javascript",
				"exec": [
					""
				]
			}
		}
	],
	"variable": [
		{
			"key": "host",
			"value": "",
			"type": "string"
		},
		{
			"key": "token",
			"value": "",
			"type": "string"
		}
	]
}